sbrfuzzy/sbrfuzzy.py
sbrfuzzy-0.0.1.dist-info/LICENSE
sbrfuzzy-0.0.1.dist-info/METADATA
sbrfuzzy-0.0.1.dist-info/WHEEL
sbrfuzzy-0.0.1.dist-info/top_level.txt
sbrfuzzy-0.0.1.dist-info/RECORD
