Metadata-Version: 2.1
Name: sbrfuzzy
Version: 0.0.1
Summary: sbrfuzzy é um módulo python para aplicações com base em sistemas baseados em regras fuzzy
Author: Henrique de Lemos Braga
License: UNKNOWN
Platform: UNKNOWN
License-File: LICENSE
Requires-Dist: matplotlib
Requires-Dist: numpy
